licenses/dep_robin
licenses/dep_pcl
licenses/README.md
licenses/dep_fmt
licenses/opencv
licenses/dep_sophus
licenses/dep_tbb
licenses/dep_gtsam
licenses/pipe_kiss
licenses/dep_eigen
licenses/dep_metis
licenses/pipe_liosam
include/evalio/types.h
include/evalio/macros.h
include/evalio/pipeline.h
evalio-0.4.0.dist-info/RECORD
evalio-0.4.0.dist-info/WHEEL
evalio-0.4.0.dist-info/entry_points.txt
evalio-0.4.0.dist-info/METADATA
evalio-0.4.0.dist-info/licenses/LICENSE.txt
evalio/_cpp.abi3.so
evalio/__init__.py
evalio/rerun.py
evalio/utils.py
evalio/stats.py
evalio/py.typed
evalio/types/extended.py
evalio/types/__init__.py
evalio/types/base.py
evalio/datasets/multi_campus.py
evalio/datasets/loaders.py
evalio/datasets/hilti_2022.py
evalio/datasets/__init__.py
evalio/datasets/oxford_spires.py
evalio/datasets/parser.py
evalio/datasets/botanic_garden.py
evalio/datasets/helipr.py
evalio/datasets/cumulti.py
evalio/datasets/newer_college_2021.py
evalio/datasets/enwide.py
evalio/datasets/base.py
evalio/datasets/newer_college_2020.py
evalio/pipelines/__init__.py
evalio/pipelines/parser.py
evalio/cli/run.py
evalio/cli/dataset_manager.py
evalio/cli/__init__.py
evalio/cli/ls.py
evalio/cli/completions.py
evalio/cli/stats.py
evalio/_cpp/__init__.pyi
evalio/_cpp/pipelines.pyi
evalio/_cpp/helpers.pyi
evalio/_cpp/types.pyi
evalio/.dylibs/libomp.dylib
share/cmake/evalio/evalioConfig.cmake
share/cmake/evalio/evalioConfigVersion.cmake
