Metadata-Version: 2.1
Name: evalio
Version: 0.4.0
Summary: Evaluate Lidar-Inertial Odometry on public datasets
Keywords: lidar,odometry,evaluation,inertial,dataset,robotics
Author-Email: Easton Potokar <contagon6@gmail.com>
Maintainer-Email: Easton Potokar <contagon6@gmail.com>
License: Copyright (c) 2025 Easton Potokar
Requires-Python: >=3.11
Requires-Dist: asteval>=1.0.6
Requires-Dist: distinctipy>=1.3.4
Requires-Dist: gdown>=5.2.0
Requires-Dist: joblib>=1.5.2
Requires-Dist: numpy
Requires-Dist: polars>=1.33.1
Requires-Dist: pyyaml>=6.0
Requires-Dist: rapidfuzz>=3.12.2
Requires-Dist: rosbags>=0.10.10
Requires-Dist: tqdm>=4.66
Requires-Dist: typer>=0.15.3
Provides-Extra: vis
Requires-Dist: rerun-sdk>=0.25; extra == "vis"
